silars/__init__.py
silars/alphalens/__init__.py
silars/alphalens/backtest.py
silars/alphalens/graph.py
silars/alphalens/perf.py
silars/alphalens/plot.py
silars/alphalens/report.py
silars/alphalens/tears.py
silars/alphalens/utils.py
silars/alphalens/weight_fns.py
silars/alphalens/zoo.py
silars/empyrical/__init__.py
silars/empyrical/deprecate.py
silars/empyrical/periods.py
silars/empyrical/stats.py
silars/empyrical/utils.py
silars/plot/__init__.py
silars/plot/graph.py
silars/plot/options.py
silars/plot/plotting.py
silars/plot/utils.py
silars/transformer/__init__.py
silars/transformer/factory.py
silars/transformer/partial.py
silars-1.1.1.dist-info/METADATA
silars-1.1.1.dist-info/WHEEL
silars-1.1.1.dist-info/top_level.txt
silars-1.1.1.dist-info/RECORD
