Metadata-Version: 2.4
Name: silars
Version: 1.1.1
License-Expression: MIT
Requires-Python: >=3.12
Requires-Dist: ipython>=9.5.0
Requires-Dist: lidb>=1.3.5
Requires-Dist: numpy>=2.3.1
Requires-Dist: pandas>=2.3.1
Requires-Dist: plotly>=6.3.0
Requires-Dist: matplotlib
Requires-Dist: polars
Requires-Dist: pyecharts
Requires-Dist: scikit-learn
Requires-Dist: statsmodels
Requires-Dist: mlflow>=3.8.1
